tkinterandcss/__init__.py
tkinterandcss/css_parser.py
tkinterandcss-0.1.0.dist-info/METADATA
tkinterandcss-0.1.0.dist-info/WHEEL
tkinterandcss-0.1.0.dist-info/top_level.txt
tkinterandcss-0.1.0.dist-info/RECORD
