Metadata-Version: 2.1
Name: tkinterandcss
Version: 0.1.0
Summary: Thư viện để áp dụng CSS cho widget Tkinter.
Home-page: https://github.com/hqmdokkai/tkinterandcss
Author: Bobby
Author-email: akirasumeragi699@gmail.com
Classifier: Programming Language :: Python :: 3
Classifier: License :: OSI Approved :: MIT License
Classifier: Operating System :: OS Independent
Requires-Python: >=3.6
Requires-Dist: tkinter
